ploomber/__init__.py
ploomber/_requests.py
ploomber/_testing_utils.py
ploomber/codediffer.py
ploomber/constants.py
ploomber/entrypoint.py
ploomber/exceptions.py
ploomber/messagecollector.py
ploomber/repo.py
ploomber/table.py
ploomber/cli/__init__.py
ploomber/cli/build.py
ploomber/cli/examples.py
ploomber/cli/install.py
ploomber/cli/interact.py
ploomber/cli/io.py
ploomber/cli/nb.py
ploomber/cli/parsers.py
ploomber/cli/plot.py
ploomber/cli/report.py
ploomber/cli/status.py
ploomber/cli/task.py
ploomber/clients/__init__.py
ploomber/clients/client.py
ploomber/clients/db.py
ploomber/clients/shell.py
ploomber/clients/storage/__init__.py
ploomber/clients/storage/abc.py
ploomber/clients/storage/aws.py
ploomber/clients/storage/gcloud.py
ploomber/clients/storage/local.py
ploomber/clients/storage/util.py
ploomber/dag/__init__.py
ploomber/dag/abstractdag.py
ploomber/dag/dag.py
ploomber/dag/dagclients.py
ploomber/dag/dagconfiguration.py
ploomber/dag/dagconfigurator.py
ploomber/dag/daglogger.py
ploomber/dag/inmemorydag.py
ploomber/dag/onlinedag.py
ploomber/dag/plot.py
ploomber/dag/superdag.py
ploomber/dag/util.py
ploomber/env/__init__.py
ploomber/env/decorators.py
ploomber/env/env.py
ploomber/env/envdict.py
ploomber/env/expand.py
ploomber/env/frozenjson.py
ploomber/env/validate.py
ploomber/executors/__init__.py
ploomber/executors/_format.py
ploomber/executors/abc.py
ploomber/executors/parallel.py
ploomber/executors/parallel_dill.py
ploomber/executors/serial.py
ploomber/io/__init__.py
ploomber/io/_commander.py
ploomber/io/_commander_tester.py
ploomber/io/_validate.py
ploomber/io/file.py
ploomber/io/loaders.py
ploomber/io/pretty_print.py
ploomber/io/serialize.py
ploomber/io/terminalwriter.py
ploomber/io/unserialize.py
ploomber/io/wcwidth.py
ploomber/jupyter/__init__.py
ploomber/jupyter/dag.py
ploomber/jupyter/manager.py
ploomber/micro/__init__.py
ploomber/micro/_micro.py
ploomber/micro/_task.py
ploomber/placeholders/__init__.py
ploomber/placeholders/abc.py
ploomber-0.23.3.dist-info/LICENSE
ploomber-0.23.3.dist-info/METADATA
ploomber-0.23.3.dist-info/WHEEL
ploomber-0.23.3.dist-info/entry_points.txt
ploomber-0.23.3.dist-info/top_level.txt
ploomber-0.23.3.dist-info/RECORD
