Metadata-Version: 2.1
Name: ploomber
Version: 0.23.3
Summary: Write maintainable, production-ready pipelines using Jupyter or your favorite text editor. Develop locally, deploy to the cloud.
Home-page: https://github.com/ploomber/ploomber
Author: Ploomber
Author-email: contact@ploomber.io
Classifier: Development Status :: 5 - Production/Stable
Classifier: Intended Audience :: Developers
Classifier: Intended Audience :: Science/Research
Classifier: License :: OSI Approved :: Apache Software License
Classifier: Operating System :: MacOS :: MacOS X
Classifier: Operating System :: Unix
Classifier: Operating System :: POSIX
Classifier: Operating System :: Microsoft :: Windows
Classifier: Programming Language :: Python
Classifier: Programming Language :: Python :: 3
Classifier: Programming Language :: Python :: 3.7
Classifier: Programming Language :: Python :: 3.8
Classifier: Programming Language :: Python :: 3.9
Classifier: Programming Language :: Python :: 3.10
License-File: LICENSE
Requires-Dist: ploomber-scaffold (>=0.3)
Requires-Dist: ploomber-engine (>=0.0.8)
Requires-Dist: ploomber-core (>=0.0.11)
Requires-Dist: pyyaml
Requires-Dist: networkx (>=2.5)
Requires-Dist: jinja2
Requires-Dist: tabulate
Requires-Dist: humanize
Requires-Dist: tqdm
Requires-Dist: posthog
Requires-Dist: sqlparse
Requires-Dist: autopep8
Requires-Dist: pycodestyle
Requires-Dist: parso
Requires-Dist: mistune
Requires-Dist: pygments
Requires-Dist: sqlalchemy
Requires-Dist: click
Requires-Dist: ipython
Requires-Dist: ipdb
Requires-Dist: pydantic
Requires-Dist: papermill
Requires-Dist: notebook (<7)
Requires-Dist: jupytext
Requires-Dist: ipykernel (>=1.5.2)
Requires-Dist: jupyter-client (>=5.3.1)
Requires-Dist: nbconvert (>=5.6.0)
Requires-Dist: nbformat
Requires-Dist: pyflakes
Provides-Extra: all
Requires-Dist: pandas ; extra == 'all'
Requires-Dist: pyarrow ; extra == 'all'
Requires-Dist: numpydoc ; extra == 'all'
Requires-Dist: requests-html ; extra == 'all'
Requires-Dist: nest-asyncio ; extra == 'all'
Provides-Extra: dev
Requires-Dist: pandas ; extra == 'dev'
Requires-Dist: pyarrow ; extra == 'dev'
Requires-Dist: numpydoc ; extra == 'dev'
Requires-Dist: requests-html ; extra == 'dev'
Requires-Dist: nest-asyncio ; extra == 'dev'
Requires-Dist: paramiko ; extra == 'dev'
Requires-Dist: boto3 ; extra == 'dev'
Requires-Dist: moto (<5) ; extra == 'dev'
Requires-Dist: google-cloud-storage ; extra == 'dev'
Requires-Dist: pytest (==7.1.*) ; extra == 'dev'
Requires-Dist: pytest-cov ; extra == 'dev'
Requires-Dist: coveralls (<3) ; extra == 'dev'
Requires-Dist: nose ; extra == 'dev'
Requires-Dist: yapf ; extra == 'dev'
Requires-Dist: flake8 ; extra == 'dev'
Requires-Dist: matplotlib ; extra == 'dev'
Requires-Dist: seaborn ; extra == 'dev'
Requires-Dist: psycopg2-binary ; extra == 'dev'
Requires-Dist: lxml ; extra == 'dev'
Requires-Dist: jupyter-server ; extra == 'dev'
Requires-Dist: notebook ; extra == 'dev'
Requires-Dist: joblib ; extra == 'dev'
Requires-Dist: cloudpickle ; extra == 'dev'
Requires-Dist: nbconvert[webpdf] ; extra == 'dev'
Requires-Dist: multiprocess ; extra == 'dev'
Requires-Dist: dill (==0.3.5.1) ; extra == 'dev'
Requires-Dist: sqlalchemy ; extra == 'dev'
Requires-Dist: twine ; extra == 'dev'
Requires-Dist: invoke ; extra == 'dev'
Requires-Dist: pkgmt ; extra == 'dev'
Requires-Dist: pygraphviz ; (python_version < "3.10") and extra == 'dev'
